lambda_bundler/__init__.py
lambda_bundler/bundler.py
lambda_bundler/dependencies.py
lambda_bundler/util.py
tests/__init__.py
tests/integration/__init__.py
tests/integration/test_bundling.py
tests/unit/__init__.py
tests/unit/test_bundler.py
tests/unit/test_dependencies.py
tests/unit/test_util.py
lambda_bundler-0.1.0.dist-info/LICENSE
lambda_bundler-0.1.0.dist-info/METADATA
lambda_bundler-0.1.0.dist-info/WHEEL
lambda_bundler-0.1.0.dist-info/top_level.txt
lambda_bundler-0.1.0.dist-info/RECORD
