Metadata-Version: 2.1
Name: lambda-bundler
Version: 0.1.0
Summary: A utility to bundle python code and/or dependencies for deployment to AWS Lambda
Home-page: https://github.com/MauriceBrg/lambda_bundler
Author: Maurice Borgmeier
License: UNKNOWN
Platform: UNKNOWN
Classifier: Intended Audience :: Developers
Classifier: Programming Language :: Python :: 3
Classifier: Programming Language :: Python :: 3.6
Classifier: Programming Language :: Python :: 3.7
Classifier: Programming Language :: Python :: 3.8
Classifier: License :: OSI Approved :: MIT License
Classifier: Operating System :: OS Independent
Requires-Python: >=3.6
Provides-Extra: dev
Requires-Dist: pylint (==2.5.3) ; extra == 'dev'
Requires-Dist: pytest (==5.4.3) ; extra == 'dev'
Requires-Dist: pytest-cov (==2.10.0) ; extra == 'dev'
Requires-Dist: setuptools (==40.8) ; extra == 'dev'
Requires-Dist: twine (==3.2.0) ; extra == 'dev'
Requires-Dist: wheel (==0.34.2) ; extra == 'dev'
